{
  "+": "+",
  "-": "-",
  "User not found": "User not found",
  "skryt": "skryt",
  "Аккаунт": "Аккаунт",
  "Войaти": "Войaти",
  "Войти": "Войти",
  "Войтиasd": "Войтиasd",
  "Выйти": "Выйти",
  "Главная": "Главная",
  "Главная страница": "Главная страница",
  "Красота": "Красота",
  "О нас": "О нас",
  "О сайте": "О сайте",
  "Обновить страницу": "Обновить страницу",
  "Произошла ошибка": "Произошла ошибка",
  "Страница не найдена": "Страница не найдена",
  "Увеличить": "Увеличить",
  "Уменьшить": "Уменьшить",
  "Форма авторизации": "Форма авторизации"
}
